elephasy/__init__.py
elephasy/hyperparam.py
elephasy/ml_model.py
elephasy/optimizers.py
elephasy/spark_model.py
elephasy/ml/__init__.py
elephasy/ml/adapter.py
elephasy/ml/params.py
elephasy/mllib/__init__.py
elephasy/mllib/adapter.py
elephasy/utils/__init__.py
elephasy/utils/functional_utils.py
elephasy/utils/rdd_utils.py
elephasy/utils/rwlock.py
elephasy-0.1.dist-info/DESCRIPTION.rst
elephasy-0.1.dist-info/METADATA
elephasy-0.1.dist-info/RECORD
elephasy-0.1.dist-info/WHEEL
elephasy-0.1.dist-info/metadata.json
elephasy-0.1.dist-info/top_level.txt
tests/__init__.py
